{"assets":{"EE3F80CCE501B7D1AB2A38BC95DE6197":{"type":"texture","index":113,"assetRequest":{"type":"slide","state":"incoming","slide":"203F753A-55D9-4D21-BB7F-6CADC42B14AA"},"url":"assets/EE3F80CCE501B7D1AB2A38BC95DE6197.svg","width":1024,"height":768},"68294B07F7CC6D712AA561FCAEF3AD1B":{"type":"texture","index":112,"assetRequest":{"type":"slide","state":"outgoing","slide":"013583A9-C00D-47C1-996D-24FE3E102001"},"url":"assets/68294B07F7CC6D712AA561FCAEF3AD1B.svg","width":1024,"height":768}},"events":[{"effects":[{"beginTime":0,"baseLayer":{"animations":[],"initialState":{"affineTransform":[1,0,0,1,0,0],"masksToBounds":true,"rotation":0,"scale":1,"position":{"pointX":512,"pointY":384},"width":1024,"sublayerTransform":[1,0,0,0,0,1,0,0,0,0,1,0,0,0,0,1],"contentsRect":{"y":0,"x":0,"width":1,"height":1},"opacity":1,"edgeAntialiasingMask":0,"height":768,"hidden":false,"anchorPoint":{"pointX":0.5,"pointY":0.5}},"objectID":"0","layers":[{"animations":[],"initialState":{"affineTransform":[1,0,0,1,0,0],"masksToBounds":false,"rotation":0,"scale":1,"position":{"pointX":512,"pointY":384},"width":1024,"sublayerTransform":[1,0,0,0,0,1,0,0,0,0,1,-0.0004922987690640373,0,0,0,1],"contentsRect":{"y":0,"x":0,"width":1,"height":1},"opacity":1,"edgeAntialiasingMask":15,"height":768,"hidden":false,"anchorPoint":{"pointX":0.5,"pointY":0.5}},"layers":[{"animations":[],"layers":[],"initialState":{"affineTransform":[1,0,0,1,0,0],"masksToBounds":false,"rotation":0,"scale":1,"position":{"pointX":512,"pointY":384},"width":1024,"sublayerTransform":[1,0,0,0,0,1,0,0,0,0,1,0,0,0,0,1],"contentsRect":{"y":0,"x":0,"width":1,"height":1},"opacity":1,"edgeAntialiasingMask":0,"height":768,"hidden":false,"anchorPoint":{"pointX":0.5,"pointY":0.5}},"texture":"EE3F80CCE501B7D1AB2A38BC95DE6197"},{"animations":[{"from":{"scalar":false},"beginTime":0,"repeatCount":0,"fillMode":"both","property":"hidden","duration":0.01,"to":{"scalar":true}}],"layers":[],"initialState":{"affineTransform":[1,0,0,1,0,0],"masksToBounds":false,"rotation":0,"scale":1,"position":{"pointX":512,"pointY":384},"width":1024,"sublayerTransform":[1,0,0,0,0,1,0,0,0,0,1,0,0,0,0,1],"contentsRect":{"y":0,"x":0,"width":1,"height":1},"opacity":1,"edgeAntialiasingMask":0,"height":768,"hidden":false,"anchorPoint":{"pointX":0.5,"pointY":0.5}},"texture":"68294B07F7CC6D712AA561FCAEF3AD1B"}]}]},"effects":[],"duration":0.01,"type":"transition","name":"none","objectID":"0"}],"automaticPlay":false,"hyperlinks":[],"accessibility":[{"text":"@WebServlet(urlPatterns = “/\")","targetRectangle":{"y":179.9999904632568,"x":70.89934539794922,"width":451.5380859375,"height":29}},{"text":"public class Length extends HttpServlet {","targetRectangle":{"y":208.9999904632568,"x":70.89934539794922,"width":617.10205078125,"height":29}},{"text":"  ","targetRectangle":{"y":237.9999904632568,"x":70.89934539794922,"width":30.1025390625,"height":29}},{"text":"  @Override","targetRectangle":{"y":266.9999904632568,"x":70.89934539794922,"width":165.56396484375,"height":29}},{"text":"  protected void doGet(HttpServletRequest request,","targetRectangle":{"y":295.9999904632568,"x":70.89934539794922,"width":752.5634765625,"height":29}},{"text":"                       HttpServletResponse response)","targetRectangle":{"y":324.9999904632568,"x":70.89934539794922,"width":782.666015625,"height":29}},{"text":"                       throws ServletException, IOException {","targetRectangle":{"y":353.9999904632568,"x":70.89934539794922,"width":918.12744140625,"height":29}},{"text":"    ","targetRectangle":{"y":382.9999904632568,"x":70.89934539794922,"width":60.205078125,"height":29}},{"text":"    int length = getResponseLength(\"https://nodesource.com/\");","targetRectangle":{"y":411.9999904632568,"x":70.89934539794922,"width":933.1787109375,"height":29}},{"text":"    response.getWriter().write(\"Length \" + length);","targetRectangle":{"y":440.9999904632568,"x":70.89934539794922,"width":767.61474609375,"height":29}},{"text":"     ","targetRectangle":{"y":469.9999904632568,"x":70.89934539794922,"width":75.25634765625,"height":29}},{"text":"  }","targetRectangle":{"y":498.9999904632568,"x":70.89934539794922,"width":45.15380859375,"height":29}},{"text":"  ","targetRectangle":{"y":527.9999904632568,"x":70.89934539794922,"width":30.1025390625,"height":29}},{"text":"  private int getResponseLength(String url)  {","targetRectangle":{"y":556.9999904632568,"x":70.89934539794922,"width":692.3583984375,"height":29}},{"text":"    //do a sync HTTP get\u2028    return html.length();","targetRectangle":{"y":585.9999904632568,"x":70.89934539794922,"width":376.28173828125,"height":58}},{"text":"  }","targetRectangle":{"y":643.9999904632568,"x":70.89934539794922,"width":45.15380859375,"height":29}},{"text":"}","targetRectangle":{"y":672.9999904632568,"x":70.89934539794922,"width":15.05126953125,"height":29}},{"text":"pasted-image.pdf","targetRectangle":{"y":702.7816162109375,"x":959.6049194335938,"width":56.26686477661133,"height":56.26686477661133}},{"text":"Basic Servlet Code","targetRectangle":{"y":53.1302604675293,"x":61.43034744262695,"width":624.7339999999999,"height":88}}],"baseLayer":{"animations":[],"initialState":{"affineTransform":[1,0,0,1,0,0],"masksToBounds":true,"rotation":0,"scale":1,"position":{"pointX":512,"pointY":384},"width":1024,"sublayerTransform":[1,0,0,0,0,1,0,0,0,0,1,0,0,0,0,1],"contentsRect":{"y":0,"x":0,"width":1,"height":1},"opacity":1,"edgeAntialiasingMask":0,"height":768,"hidden":false,"anchorPoint":{"pointX":0.5,"pointY":0.5}},"objectID":"0","layers":[{"animations":[],"initialState":{"affineTransform":[1,0,0,1,0,0],"masksToBounds":false,"rotation":0,"scale":1,"position":{"pointX":512,"pointY":384},"width":1024,"sublayerTransform":[1,0,0,0,0,1,0,0,0,0,1,-0.0004922987690640373,0,0,0,1],"contentsRect":{"y":0,"x":0,"width":1,"height":1},"opacity":1,"edgeAntialiasingMask":15,"height":768,"hidden":false,"anchorPoint":{"pointX":0.5,"pointY":0.5}},"layers":[{"animations":[],"layers":[],"initialState":{"affineTransform":[1,0,0,1,0,0],"masksToBounds":false,"rotation":0,"scale":1,"position":{"pointX":512,"pointY":384},"width":1024,"sublayerTransform":[1,0,0,0,0,1,0,0,0,0,1,0,0,0,0,1],"contentsRect":{"y":0,"x":0,"width":1,"height":1},"opacity":1,"edgeAntialiasingMask":0,"height":768,"hidden":false,"anchorPoint":{"pointX":0.5,"pointY":0.5}},"texture":"68294B07F7CC6D712AA561FCAEF3AD1B"}]}]}}]}