{"assets":{"46B37BF333FDD983A8FBC88F1539B444":{"type":"texture","index":508,"assetRequest":{"type":"slide","state":"contents","slide":"2C4F0252-3A03-440E-AC7C-D6360E787A40"},"url":"assets/46B37BF333FDD983A8FBC88F1539B444.svg","width":174,"height":58},"BDE3A89D37FB90520BA60BA16E672BEC":{"type":"texture","index":509,"assetRequest":{"type":"slide","state":"outgoing","slide":"2C4F0252-3A03-440E-AC7C-D6360E787A40"},"url":"assets/BDE3A89D37FB90520BA60BA16E672BEC.svg","width":1024,"height":768},"79A2DF10E1AF552D908C866D02D14BEB":{"type":"texture","index":504,"assetRequest":{"type":"slide","state":"contents","slide":"2C4F0252-3A03-440E-AC7C-D6360E787A40"},"url":"assets/79A2DF10E1AF552D908C866D02D14BEB.svg","width":973,"height":460},"2C9DB90032D83BB24BF98C4AE488D5EA":{"type":"texture","index":506,"assetRequest":{"type":"slide","state":"contents","slide":"2C4F0252-3A03-440E-AC7C-D6360E787A40"},"url":"assets/2C9DB90032D83BB24BF98C4AE488D5EA.svg","width":93,"height":48},"B1BFF7B2FFA1C6EDC49D405D0E31B9AB":{"type":"texture","index":510,"assetRequest":{"type":"slide","state":"incoming","slide":"16EDFEA7-CE1D-4341-8147-8B4FCF37B41C"},"url":"assets/B1BFF7B2FFA1C6EDC49D405D0E31B9AB.svg","width":1024,"height":768},"9E6D1E412FF49425C906C5740AF4710B":{"type":"texture","index":503,"assetRequest":{"type":"slide","state":"contents","slide":"2C4F0252-3A03-440E-AC7C-D6360E787A40"},"url":"assets/9E6D1E412FF49425C906C5740AF4710B.svg","width":59,"height":60},"EABA7B6053AB46FA718D41E94BE9775A":{"type":"texture","index":505,"assetRequest":{"type":"slide","state":"contents","slide":"2C4F0252-3A03-440E-AC7C-D6360E787A40"},"url":"assets/EABA7B6053AB46FA718D41E94BE9775A.svg","width":643,"height":49},"D1A4DB96B5C9DBC588DC0D604E86AF00":{"type":"texture","index":507,"assetRequest":{"type":"slide","state":"contents","slide":"2C4F0252-3A03-440E-AC7C-D6360E787A40"},"url":"assets/D1A4DB96B5C9DBC588DC0D604E86AF00.svg","width":184,"height":48},"B7EE55197648951AB1FCAAA844753D44":{"type":"texture","index":502,"assetRequest":{"type":"slide","state":"contents","slide":"2C4F0252-3A03-440E-AC7C-D6360E787A40"},"url":"assets/B7EE55197648951AB1FCAAA844753D44.svg","width":1024,"height":768}},"events":[{"effects":[{"beginTime":0,"baseLayer":{"animations":[],"initialState":{"affineTransform":[1,0,0,1,0,0],"masksToBounds":false,"rotation":0,"scale":1,"position":{"pointX":467.3267021179199,"pointY":395.5102000832558},"width":639.4781112670898,"sublayerTransform":[1,0,0,0,0,1,0,0,0,0,1,0,0,0,0,1],"contentsRect":{"y":0,"x":0,"width":1,"height":1},"opacity":0.3331785500049591,"edgeAntialiasingMask":15,"height":45.08314430713654,"hidden":false,"anchorPoint":{"pointX":0.5,"pointY":0.5}},"objectID":"3FB22E02-9D9B-4AA0-AF2A-AE81C85A2A79","layers":[{"animations":[],"initialState":{"affineTransform":[1,0,0,1,0,0],"masksToBounds":false,"rotation":0,"scale":1,"position":{"pointX":364.412353515625,"pointY":11.0313720703125},"width":639.4781112670898,"sublayerTransform":[1,0,0,0,0,1,0,0,0,0,1,-0.0004922987690640373,0,0,0,1],"contentsRect":{"y":0,"x":0,"width":1,"height":1},"opacity":1,"edgeAntialiasingMask":15,"height":45.08314430713654,"hidden":false,"anchorPoint":{"pointX":0.5698589945378466,"pointY":0.2446895006958568}},"layers":[{"animations":[{"repeatCount":0,"animations":[{"from":{"scalar":0},"beginTime":0,"repeatCount":0,"fillMode":"both","property":"opacity","duration":0.2,"timingFunction":"easeInEaseOut","to":{"scalar":1}},{"from":{"scalar":false},"beginTime":0,"repeatCount":0,"fillMode":"forwards","property":"hidden","duration":0.2,"to":{"scalar":false}}],"beginTime":1e-100,"fillMode":"both","duration":0.2}],"layers":[],"initialState":{"affineTransform":[1,0,0,1,0,0],"masksToBounds":false,"rotation":0,"scale":1,"position":{"pointX":319.912353515625,"pointY":22.5313720703125},"width":643,"sublayerTransform":[1,0,0,0,0,1,0,0,0,0,1,0,0,0,0,1],"contentsRect":{"y":0,"x":0,"width":1,"height":1},"opacity":1,"edgeAntialiasingMask":0,"height":49,"hidden":true,"anchorPoint":{"pointX":0.5,"pointY":0.5}},"texture":"EABA7B6053AB46FA718D41E94BE9775A"}]}]},"effects":[],"duration":0.2,"type":"buildIn","attributes":{"direction":0},"name":"com.apple.iWork.Keynote.FromDarkness","objectID":"3FB22E02-9D9B-4AA0-AF2A-AE81C85A2A79"}],"automaticPlay":true,"hyperlinks":[],"accessibility":[{"text":"Node","targetRectangle":{"y":53.1302604675293,"x":61.43034744262695,"width":178.485,"height":88}},{"text":"var http   = require('http'),","targetRectangle":{"y":195.9999990463257,"x":69.56600952148438,"width":453.9462890625,"height":30}},{"text":"\t\t request = require('request');","targetRectangle":{"y":225.9999990463257,"x":69.56600952148438,"width":505.599609375,"height":30}},{"text":"http.createServer(function (req, res) {","targetRectangle":{"y":285.9999990463257,"x":69.56600952148438,"width":610.4794921875,"height":30}},{"text":"  try {","targetRectangle":{"y":315.9999990463257,"x":69.56600952148438,"width":109.5732421875,"height":30}},{"text":"    request.get('https://nodesource.com', function(e, r, b) { \u2028      throw new Error('Error');","targetRectangle":{"y":345.9999990463257,"x":69.56600952148438,"width":977.505859375,"height":70}},{"text":"      res.writeHead(200, {'Content-Type': 'text/plain'});","targetRectangle":{"y":415.9999990463257,"x":69.56600952148438,"width":892.2392578125,"height":30}},{"text":"      res.end('Length :' + b.length);","targetRectangle":{"y":445.9999990463257,"x":69.56600952148438,"width":579.1728515625,"height":30}},{"text":"                              ","targetRectangle":{"y":475.9999990463257,"x":69.56600952148438,"width":469.599609375,"height":30}},{"text":"    });","targetRectangle":{"y":505.9999990463257,"x":69.56600952148438,"width":109.5732421875,"height":30}},{"text":"  }\u2028  catch(e) {}","targetRectangle":{"y":535.9999990463257,"x":69.56600952148438,"width":203.4931640625,"height":60}},{"text":"}).listen(8000, '127.0.0.1');","targetRectangle":{"y":625.9999990463257,"x":69.56600952148438,"width":453.9462890625,"height":30}},{"text":"pasted-image.pdf","targetRectangle":{"y":702.7816162109375,"x":959.6049194335938,"width":56.26686477661133,"height":56.26686477661133}}],"baseLayer":{"animations":[],"initialState":{"affineTransform":[1,0,0,1,0,0],"masksToBounds":true,"rotation":0,"scale":1,"position":{"pointX":512,"pointY":384},"width":1024,"sublayerTransform":[1,0,0,0,0,1,0,0,0,0,1,0,0,0,0,1],"contentsRect":{"y":0,"x":0,"width":1,"height":1},"opacity":1,"edgeAntialiasingMask":0,"height":768,"hidden":false,"anchorPoint":{"pointX":0.5,"pointY":0.5}},"layers":[{"animations":[],"initialState":{"affineTransform":[1,0,0,1,0,0],"masksToBounds":false,"rotation":0,"scale":1,"position":{"pointX":512,"pointY":384},"width":1024,"sublayerTransform":[1,0,0,0,0,1,0,0,0,0,1,0,0,0,0,1],"contentsRect":{"y":0,"x":0,"width":1,"height":1},"opacity":1,"edgeAntialiasingMask":15,"height":768,"hidden":false,"anchorPoint":{"pointX":0.5,"pointY":0.5}},"layers":[{"animations":[],"initialState":{"affineTransform":[1,0,0,1,0,0],"masksToBounds":false,"rotation":0,"scale":1,"position":{"pointX":512,"pointY":384},"width":1024,"sublayerTransform":[1,0,0,0,0,1,0,0,0,0,1,0,0,0,0,1],"contentsRect":{"y":0,"x":0,"width":1,"height":1},"opacity":1,"edgeAntialiasingMask":15,"height":768,"hidden":false,"anchorPoint":{"pointX":0.5,"pointY":0.5}},"layers":[{"animations":[],"layers":[],"initialState":{"affineTransform":[1,0,0,1,0,0],"masksToBounds":false,"rotation":0,"scale":1,"position":{"pointX":512,"pointY":384},"width":1024,"sublayerTransform":[1,0,0,0,0,1,0,0,0,0,1,0,0,0,0,1],"contentsRect":{"y":0,"x":0,"width":1,"height":1},"opacity":1,"edgeAntialiasingMask":0,"height":768,"hidden":false,"anchorPoint":{"pointX":0.5,"pointY":0.5}},"texture":"B7EE55197648951AB1FCAAA844753D44"}]}]},{"animations":[],"initialState":{"affineTransform":[1,0,0,1,0,0],"masksToBounds":false,"rotation":0,"scale":1,"position":{"pointX":512,"pointY":384},"width":1024,"sublayerTransform":[1,0,0,0,0,1,0,0,0,0,1,0,0,0,0,1],"contentsRect":{"y":0,"x":0,"width":1,"height":1},"opacity":1,"edgeAntialiasingMask":15,"height":768,"hidden":false,"anchorPoint":{"pointX":0.5,"pointY":0.5}},"layers":[{"animations":[],"initialState":{"affineTransform":[1,0,0,1,0,0],"masksToBounds":false,"rotation":0,"scale":1,"position":{"pointX":987.7383518218994,"pointY":730.9150485992432},"width":56.26686477661133,"sublayerTransform":[1,0,0,0,0,1,0,0,0,0,1,0,0,0,0,1],"contentsRect":{"y":0,"x":0,"width":1,"height":1},"opacity":1,"edgeAntialiasingMask":15,"height":56.26686477661133,"hidden":false,"anchorPoint":{"pointX":0.5,"pointY":0.5}},"objectID":"5C68F28F-D825-44B3-880E-6B6850165C33","layers":[{"animations":[],"layers":[],"initialState":{"affineTransform":[1,0,0,1,0,0],"masksToBounds":false,"rotation":0,"scale":1,"position":{"pointX":27.89508056640625,"pointY":28.2183837890625},"width":59,"sublayerTransform":[1,0,0,0,0,1,0,0,0,0,1,0,0,0,0,1],"contentsRect":{"y":0,"x":0,"width":1,"height":1},"opacity":1,"edgeAntialiasingMask":0,"height":60,"hidden":false,"anchorPoint":{"pointX":0.5,"pointY":0.5}},"texture":"9E6D1E412FF49425C906C5740AF4710B"}]}]},{"animations":[],"initialState":{"affineTransform":[1,0,0,1,0,0],"masksToBounds":false,"rotation":0,"scale":1,"position":{"pointX":512,"pointY":384},"width":1024,"sublayerTransform":[1,0,0,0,0,1,0,0,0,0,1,0,0,0,0,1],"contentsRect":{"y":0,"x":0,"width":1,"height":1},"opacity":1,"edgeAntialiasingMask":15,"height":768,"hidden":false,"anchorPoint":{"pointX":0.5,"pointY":0.5}},"layers":[{"animations":[],"initialState":{"affineTransform":[1,0,0,1,0,0],"masksToBounds":false,"rotation":0,"scale":1,"position":{"pointX":605.2488746643066,"pointY":441},"width":1079.365730285645,"sublayerTransform":[1,0,0,0,0,1,0,0,0,0,1,0,0,0,0,1],"contentsRect":{"y":0,"x":0,"width":1,"height":1},"opacity":1,"edgeAntialiasingMask":15,"height":498.0000019073486,"hidden":false,"anchorPoint":{"pointX":0.5,"pointY":0.5}},"objectID":"A79AB04E-7049-4736-98BE-A22DD2DC608B","layers":[{"animations":[],"layers":[],"initialState":{"affineTransform":[1,0,0,1,0,0],"masksToBounds":false,"rotation":0,"scale":1,"position":{"pointX":488.9339904785156,"pointY":234.0000009536743},"width":973,"sublayerTransform":[1,0,0,0,0,1,0,0,0,0,1,0,0,0,0,1],"contentsRect":{"y":0,"x":0,"width":1,"height":1},"opacity":1,"edgeAntialiasingMask":0,"height":460,"hidden":false,"anchorPoint":{"pointX":0.5,"pointY":0.5}},"texture":"79A2DF10E1AF552D908C866D02D14BEB"}]}]},{"animations":[],"initialState":{"affineTransform":[1,0,0,1,0,0],"masksToBounds":false,"rotation":0,"scale":1,"position":{"pointX":512,"pointY":384},"width":1024,"sublayerTransform":[1,0,0,0,0,1,0,0,0,0,1,0,0,0,0,1],"contentsRect":{"y":0,"x":0,"width":1,"height":1},"opacity":1,"edgeAntialiasingMask":15,"height":768,"hidden":false,"anchorPoint":{"pointX":0.5,"pointY":0.5}},"layers":[{"animations":[],"initialState":{"affineTransform":[1,0,0,1,0,0],"masksToBounds":false,"rotation":0,"scale":1,"position":{"pointX":467.3267021179199,"pointY":395.5102000832558},"width":639.4781112670898,"sublayerTransform":[1,0,0,0,0,1,0,0,0,0,1,0,0,0,0,1],"contentsRect":{"y":0,"x":0,"width":1,"height":1},"opacity":0.3331785500049591,"edgeAntialiasingMask":15,"height":45.08314430713654,"hidden":false,"anchorPoint":{"pointX":0.5,"pointY":0.5}},"objectID":"3FB22E02-9D9B-4AA0-AF2A-AE81C85A2A79","layers":[{"animations":[],"layers":[],"initialState":{"affineTransform":[1,0,0,1,0,0],"masksToBounds":false,"rotation":0,"scale":1,"position":{"pointX":319.912353515625,"pointY":22.5313720703125},"width":643,"sublayerTransform":[1,0,0,0,0,1,0,0,0,0,1,0,0,0,0,1],"contentsRect":{"y":0,"x":0,"width":1,"height":1},"opacity":1,"edgeAntialiasingMask":0,"height":49,"hidden":true,"anchorPoint":{"pointX":0.5,"pointY":0.5}},"texture":"EABA7B6053AB46FA718D41E94BE9775A"}]}]},{"animations":[],"initialState":{"affineTransform":[1,0,0,1,0,0],"masksToBounds":false,"rotation":0,"scale":1,"position":{"pointX":512,"pointY":384},"width":1024,"sublayerTransform":[1,0,0,0,0,1,0,0,0,0,1,0,0,0,0,1],"contentsRect":{"y":0,"x":0,"width":1,"height":1},"opacity":1,"edgeAntialiasingMask":15,"height":768,"hidden":false,"anchorPoint":{"pointX":0.5,"pointY":0.5}},"layers":[{"animations":[],"initialState":{"affineTransform":[1,0,0,1,0,0],"masksToBounds":false,"rotation":0,"scale":1,"position":{"pointX":145.3219459056854,"pointY":332.5658336281776},"width":90.09546041488647,"sublayerTransform":[1,0,0,0,0,1,0,0,0,0,1,0,0,0,0,1],"contentsRect":{"y":0,"x":0,"width":1,"height":1},"opacity":0.3331785500049591,"edgeAntialiasingMask":15,"height":45.08314430713654,"hidden":false,"anchorPoint":{"pointX":0.5,"pointY":0.5}},"objectID":"296FBA55-122C-429E-86FB-23582E5ED76E","layers":[{"animations":[],"layers":[],"initialState":{"affineTransform":[1,0,0,1,0,0],"masksToBounds":false,"rotation":0,"scale":1,"position":{"pointX":45.22578430175781,"pointY":22.97573852539062},"width":93,"sublayerTransform":[1,0,0,0,0,1,0,0,0,0,1,0,0,0,0,1],"contentsRect":{"y":0,"x":0,"width":1,"height":1},"opacity":1,"edgeAntialiasingMask":0,"height":48,"hidden":true,"anchorPoint":{"pointX":0.5,"pointY":0.5}},"texture":"2C9DB90032D83BB24BF98C4AE488D5EA"}]}]},{"animations":[],"initialState":{"affineTransform":[1,0,0,1,0,0],"masksToBounds":false,"rotation":0,"scale":1,"position":{"pointX":512,"pointY":384},"width":1024,"sublayerTransform":[1,0,0,0,0,1,0,0,0,0,1,0,0,0,0,1],"contentsRect":{"y":0,"x":0,"width":1,"height":1},"opacity":1,"edgeAntialiasingMask":15,"height":768,"hidden":false,"anchorPoint":{"pointX":0.5,"pointY":0.5}},"layers":[{"animations":[],"initialState":{"affineTransform":[1,0,0,1,0,0],"masksToBounds":false,"rotation":0,"scale":1,"position":{"pointX":190.897928237915,"pointY":580.1560741066933},"width":181.2474250793457,"sublayerTransform":[1,0,0,0,0,1,0,0,0,0,1,0,0,0,0,1],"contentsRect":{"y":0,"x":0,"width":1,"height":1},"opacity":0.3331785500049591,"edgeAntialiasingMask":15,"height":45.08314430713654,"hidden":false,"anchorPoint":{"pointX":0.5,"pointY":0.5}},"objectID":"480AFC97-2829-4EB4-A164-FF9D5C6DDD41","layers":[{"animations":[],"layers":[],"initialState":{"affineTransform":[1,0,0,1,0,0],"masksToBounds":false,"rotation":0,"scale":1,"position":{"pointX":90.72578430175781,"pointY":22.385498046875},"width":184,"sublayerTransform":[1,0,0,0,0,1,0,0,0,0,1,0,0,0,0,1],"contentsRect":{"y":0,"x":0,"width":1,"height":1},"opacity":1,"edgeAntialiasingMask":0,"height":48,"hidden":true,"anchorPoint":{"pointX":0.5,"pointY":0.5}},"texture":"D1A4DB96B5C9DBC588DC0D604E86AF00"}]}]},{"animations":[],"initialState":{"affineTransform":[1,0,0,1,0,0],"masksToBounds":false,"rotation":0,"scale":1,"position":{"pointX":512,"pointY":384},"width":1024,"sublayerTransform":[1,0,0,0,0,1,0,0,0,0,1,0,0,0,0,1],"contentsRect":{"y":0,"x":0,"width":1,"height":1},"opacity":1,"edgeAntialiasingMask":15,"height":768,"hidden":false,"anchorPoint":{"pointX":0.5,"pointY":0.5}},"layers":[{"animations":[],"initialState":{"affineTransform":[1,0,0,1,0,0],"masksToBounds":false,"rotation":0,"scale":1,"position":{"pointX":470.2907304763794,"pointY":97.06479352712631},"width":825.7207660675049,"sublayerTransform":[1,0,0,0,0,1,0,0,0,0,1,0,0,0,0,1],"contentsRect":{"y":0,"x":0,"width":1,"height":1},"opacity":1,"edgeAntialiasingMask":15,"height":95.86906611919403,"hidden":false,"anchorPoint":{"pointX":0.5,"pointY":0.5}},"objectID":"7FDEDC4A-7AC6-48C7-B69A-38F1F6ED0C7D","layers":[{"animations":[],"layers":[],"initialState":{"affineTransform":[1,0,0,1,0,0],"masksToBounds":false,"rotation":0,"scale":1,"position":{"pointX":94.56965255737305,"pointY":49.8697395324707},"width":174,"sublayerTransform":[1,0,0,0,0,1,0,0,0,0,1,0,0,0,0,1],"contentsRect":{"y":0,"x":0,"width":1,"height":1},"opacity":1,"edgeAntialiasingMask":0,"height":58,"hidden":false,"anchorPoint":{"pointX":0.5,"pointY":0.5}},"texture":"46B37BF333FDD983A8FBC88F1539B444"}]}]}]}},{"effects":[{"beginTime":0,"baseLayer":{"animations":[],"initialState":{"affineTransform":[1,0,0,1,0,0],"masksToBounds":false,"rotation":0,"scale":1,"position":{"pointX":145.3219459056854,"pointY":332.5658336281776},"width":90.09546041488647,"sublayerTransform":[1,0,0,0,0,1,0,0,0,0,1,0,0,0,0,1],"contentsRect":{"y":0,"x":0,"width":1,"height":1},"opacity":0.3331785500049591,"edgeAntialiasingMask":15,"height":45.08314430713654,"hidden":false,"anchorPoint":{"pointX":0.5,"pointY":0.5}},"objectID":"296FBA55-122C-429E-86FB-23582E5ED76E","layers":[{"animations":[],"initialState":{"affineTransform":[1,0,0,1,0,0],"masksToBounds":false,"rotation":0,"scale":1,"position":{"pointX":411.7257843017578,"pointY":73.97573852539062},"width":90.09546041488647,"sublayerTransform":[1,0,0,0,0,1,0,0,0,0,1,-0.0004922987690640373,0,0,0,1],"contentsRect":{"y":0,"x":0,"width":1,"height":1},"opacity":1,"edgeAntialiasingMask":15,"height":45.08314430713654,"hidden":false,"anchorPoint":{"pointX":4.569883792210782,"pointY":1.640873538487431}},"layers":[{"animations":[{"repeatCount":0,"animations":[{"from":{"scalar":0},"beginTime":0,"repeatCount":0,"fillMode":"both","property":"opacity","duration":0.2,"timingFunction":"easeInEaseOut","to":{"scalar":1}},{"from":{"scalar":false},"beginTime":0,"repeatCount":0,"fillMode":"forwards","property":"hidden","duration":0.2,"to":{"scalar":false}}],"beginTime":1e-100,"fillMode":"both","duration":0.2}],"layers":[],"initialState":{"affineTransform":[1,0,0,1,0,0],"masksToBounds":false,"rotation":0,"scale":1,"position":{"pointX":45.22578430175781,"pointY":22.97573852539062},"width":93,"sublayerTransform":[1,0,0,0,0,1,0,0,0,0,1,0,0,0,0,1],"contentsRect":{"y":0,"x":0,"width":1,"height":1},"opacity":1,"edgeAntialiasingMask":0,"height":48,"hidden":true,"anchorPoint":{"pointX":0.5,"pointY":0.5}},"texture":"2C9DB90032D83BB24BF98C4AE488D5EA"}]}]},"effects":[],"duration":0.2,"type":"buildIn","attributes":{"direction":0},"name":"com.apple.iWork.Keynote.FromDarkness","objectID":"296FBA55-122C-429E-86FB-23582E5ED76E"},{"beginTime":0,"baseLayer":{"animations":[],"initialState":{"affineTransform":[1,0,0,1,0,0],"masksToBounds":false,"rotation":0,"scale":1,"position":{"pointX":190.897928237915,"pointY":580.1560741066933},"width":181.2474250793457,"sublayerTransform":[1,0,0,0,0,1,0,0,0,0,1,0,0,0,0,1],"contentsRect":{"y":0,"x":0,"width":1,"height":1},"opacity":0.3331785500049591,"edgeAntialiasingMask":15,"height":45.08314430713654,"hidden":false,"anchorPoint":{"pointX":0.5,"pointY":0.5}},"objectID":"480AFC97-2829-4EB4-A164-FF9D5C6DDD41","layers":[{"animations":[],"initialState":{"affineTransform":[1,0,0,1,0,0],"masksToBounds":false,"rotation":0,"scale":1,"position":{"pointX":411.7257843017578,"pointY":-173.614501953125},"width":181.2474250793457,"sublayerTransform":[1,0,0,0,0,1,0,0,0,0,1,-0.0004922987690640373,0,0,0,1],"contentsRect":{"y":0,"x":0,"width":1,"height":1},"opacity":1,"edgeAntialiasingMask":15,"height":45.08314430713654,"hidden":false,"anchorPoint":{"pointX":2.271622805794423,"pointY":-3.850984766509338}},"layers":[{"animations":[{"repeatCount":0,"animations":[{"from":{"scalar":0},"beginTime":0,"repeatCount":0,"fillMode":"both","property":"opacity","duration":0.2,"timingFunction":"easeInEaseOut","to":{"scalar":1}},{"from":{"scalar":false},"beginTime":0,"repeatCount":0,"fillMode":"forwards","property":"hidden","duration":0.2,"to":{"scalar":false}}],"beginTime":1e-100,"fillMode":"both","duration":0.2}],"layers":[],"initialState":{"affineTransform":[1,0,0,1,0,0],"masksToBounds":false,"rotation":0,"scale":1,"position":{"pointX":90.72578430175781,"pointY":22.385498046875},"width":184,"sublayerTransform":[1,0,0,0,0,1,0,0,0,0,1,0,0,0,0,1],"contentsRect":{"y":0,"x":0,"width":1,"height":1},"opacity":1,"edgeAntialiasingMask":0,"height":48,"hidden":true,"anchorPoint":{"pointX":0.5,"pointY":0.5}},"texture":"D1A4DB96B5C9DBC588DC0D604E86AF00"}]}]},"effects":[],"duration":0.2,"type":"buildIn","attributes":{"direction":0},"name":"com.apple.iWork.Keynote.FromDarkness","objectID":"480AFC97-2829-4EB4-A164-FF9D5C6DDD41"}],"automaticPlay":false,"hyperlinks":[],"accessibility":[{"text":"Node","targetRectangle":{"y":53.1302604675293,"x":61.43034744262695,"width":178.485,"height":88}},{"text":"var http   = require('http'),","targetRectangle":{"y":195.9999990463257,"x":69.56600952148438,"width":453.9462890625,"height":30}},{"text":"\t\t request = require('request');","targetRectangle":{"y":225.9999990463257,"x":69.56600952148438,"width":505.599609375,"height":30}},{"text":"http.createServer(function (req, res) {","targetRectangle":{"y":285.9999990463257,"x":69.56600952148438,"width":610.4794921875,"height":30}},{"text":"  try {","targetRectangle":{"y":315.9999990463257,"x":69.56600952148438,"width":109.5732421875,"height":30}},{"text":"    request.get('https://nodesource.com', function(e, r, b) { \u2028      throw new Error('Error');","targetRectangle":{"y":345.9999990463257,"x":69.56600952148438,"width":977.505859375,"height":70}},{"text":"      res.writeHead(200, {'Content-Type': 'text/plain'});","targetRectangle":{"y":415.9999990463257,"x":69.56600952148438,"width":892.2392578125,"height":30}},{"text":"      res.end('Length :' + b.length);","targetRectangle":{"y":445.9999990463257,"x":69.56600952148438,"width":579.1728515625,"height":30}},{"text":"                              ","targetRectangle":{"y":475.9999990463257,"x":69.56600952148438,"width":469.599609375,"height":30}},{"text":"    });","targetRectangle":{"y":505.9999990463257,"x":69.56600952148438,"width":109.5732421875,"height":30}},{"text":"  }\u2028  catch(e) {}","targetRectangle":{"y":535.9999990463257,"x":69.56600952148438,"width":203.4931640625,"height":60}},{"text":"}).listen(8000, '127.0.0.1');","targetRectangle":{"y":625.9999990463257,"x":69.56600952148438,"width":453.9462890625,"height":30}},{"text":"pasted-image.pdf","targetRectangle":{"y":702.7816162109375,"x":959.6049194335938,"width":56.26686477661133,"height":56.26686477661133}}],"baseLayer":{"animations":[],"initialState":{"affineTransform":[1,0,0,1,0,0],"masksToBounds":true,"rotation":0,"scale":1,"position":{"pointX":512,"pointY":384},"width":1024,"sublayerTransform":[1,0,0,0,0,1,0,0,0,0,1,0,0,0,0,1],"contentsRect":{"y":0,"x":0,"width":1,"height":1},"opacity":1,"edgeAntialiasingMask":0,"height":768,"hidden":false,"anchorPoint":{"pointX":0.5,"pointY":0.5}},"layers":[{"animations":[],"initialState":{"affineTransform":[1,0,0,1,0,0],"masksToBounds":false,"rotation":0,"scale":1,"position":{"pointX":512,"pointY":384},"width":1024,"sublayerTransform":[1,0,0,0,0,1,0,0,0,0,1,0,0,0,0,1],"contentsRect":{"y":0,"x":0,"width":1,"height":1},"opacity":1,"edgeAntialiasingMask":15,"height":768,"hidden":false,"anchorPoint":{"pointX":0.5,"pointY":0.5}},"layers":[{"animations":[],"initialState":{"affineTransform":[1,0,0,1,0,0],"masksToBounds":false,"rotation":0,"scale":1,"position":{"pointX":512,"pointY":384},"width":1024,"sublayerTransform":[1,0,0,0,0,1,0,0,0,0,1,0,0,0,0,1],"contentsRect":{"y":0,"x":0,"width":1,"height":1},"opacity":1,"edgeAntialiasingMask":15,"height":768,"hidden":false,"anchorPoint":{"pointX":0.5,"pointY":0.5}},"layers":[{"animations":[],"layers":[],"initialState":{"affineTransform":[1,0,0,1,0,0],"masksToBounds":false,"rotation":0,"scale":1,"position":{"pointX":512,"pointY":384},"width":1024,"sublayerTransform":[1,0,0,0,0,1,0,0,0,0,1,0,0,0,0,1],"contentsRect":{"y":0,"x":0,"width":1,"height":1},"opacity":1,"edgeAntialiasingMask":0,"height":768,"hidden":false,"anchorPoint":{"pointX":0.5,"pointY":0.5}},"texture":"B7EE55197648951AB1FCAAA844753D44"}]}]},{"animations":[],"initialState":{"affineTransform":[1,0,0,1,0,0],"masksToBounds":false,"rotation":0,"scale":1,"position":{"pointX":512,"pointY":384},"width":1024,"sublayerTransform":[1,0,0,0,0,1,0,0,0,0,1,0,0,0,0,1],"contentsRect":{"y":0,"x":0,"width":1,"height":1},"opacity":1,"edgeAntialiasingMask":15,"height":768,"hidden":false,"anchorPoint":{"pointX":0.5,"pointY":0.5}},"layers":[{"animations":[],"initialState":{"affineTransform":[1,0,0,1,0,0],"masksToBounds":false,"rotation":0,"scale":1,"position":{"pointX":987.7383518218994,"pointY":730.9150485992432},"width":56.26686477661133,"sublayerTransform":[1,0,0,0,0,1,0,0,0,0,1,0,0,0,0,1],"contentsRect":{"y":0,"x":0,"width":1,"height":1},"opacity":1,"edgeAntialiasingMask":15,"height":56.26686477661133,"hidden":false,"anchorPoint":{"pointX":0.5,"pointY":0.5}},"objectID":"5C68F28F-D825-44B3-880E-6B6850165C33","layers":[{"animations":[],"layers":[],"initialState":{"affineTransform":[1,0,0,1,0,0],"masksToBounds":false,"rotation":0,"scale":1,"position":{"pointX":27.89508056640625,"pointY":28.2183837890625},"width":59,"sublayerTransform":[1,0,0,0,0,1,0,0,0,0,1,0,0,0,0,1],"contentsRect":{"y":0,"x":0,"width":1,"height":1},"opacity":1,"edgeAntialiasingMask":0,"height":60,"hidden":false,"anchorPoint":{"pointX":0.5,"pointY":0.5}},"texture":"9E6D1E412FF49425C906C5740AF4710B"}]}]},{"animations":[],"initialState":{"affineTransform":[1,0,0,1,0,0],"masksToBounds":false,"rotation":0,"scale":1,"position":{"pointX":512,"pointY":384},"width":1024,"sublayerTransform":[1,0,0,0,0,1,0,0,0,0,1,0,0,0,0,1],"contentsRect":{"y":0,"x":0,"width":1,"height":1},"opacity":1,"edgeAntialiasingMask":15,"height":768,"hidden":false,"anchorPoint":{"pointX":0.5,"pointY":0.5}},"layers":[{"animations":[],"initialState":{"affineTransform":[1,0,0,1,0,0],"masksToBounds":false,"rotation":0,"scale":1,"position":{"pointX":605.2488746643066,"pointY":441},"width":1079.365730285645,"sublayerTransform":[1,0,0,0,0,1,0,0,0,0,1,0,0,0,0,1],"contentsRect":{"y":0,"x":0,"width":1,"height":1},"opacity":1,"edgeAntialiasingMask":15,"height":498.0000019073486,"hidden":false,"anchorPoint":{"pointX":0.5,"pointY":0.5}},"objectID":"A79AB04E-7049-4736-98BE-A22DD2DC608B","layers":[{"animations":[],"layers":[],"initialState":{"affineTransform":[1,0,0,1,0,0],"masksToBounds":false,"rotation":0,"scale":1,"position":{"pointX":488.9339904785156,"pointY":234.0000009536743},"width":973,"sublayerTransform":[1,0,0,0,0,1,0,0,0,0,1,0,0,0,0,1],"contentsRect":{"y":0,"x":0,"width":1,"height":1},"opacity":1,"edgeAntialiasingMask":0,"height":460,"hidden":false,"anchorPoint":{"pointX":0.5,"pointY":0.5}},"texture":"79A2DF10E1AF552D908C866D02D14BEB"}]}]},{"animations":[],"initialState":{"affineTransform":[1,0,0,1,0,0],"masksToBounds":false,"rotation":0,"scale":1,"position":{"pointX":512,"pointY":384},"width":1024,"sublayerTransform":[1,0,0,0,0,1,0,0,0,0,1,0,0,0,0,1],"contentsRect":{"y":0,"x":0,"width":1,"height":1},"opacity":1,"edgeAntialiasingMask":15,"height":768,"hidden":false,"anchorPoint":{"pointX":0.5,"pointY":0.5}},"layers":[{"animations":[],"initialState":{"affineTransform":[1,0,0,1,0,0],"masksToBounds":false,"rotation":0,"scale":1,"position":{"pointX":467.3267021179199,"pointY":395.5102000832558},"width":639.4781112670898,"sublayerTransform":[1,0,0,0,0,1,0,0,0,0,1,0,0,0,0,1],"contentsRect":{"y":0,"x":0,"width":1,"height":1},"opacity":0.3331785500049591,"edgeAntialiasingMask":15,"height":45.08314430713654,"hidden":false,"anchorPoint":{"pointX":0.5,"pointY":0.5}},"objectID":"3FB22E02-9D9B-4AA0-AF2A-AE81C85A2A79","layers":[{"animations":[],"layers":[],"initialState":{"affineTransform":[1,0,0,1,0,0],"masksToBounds":false,"rotation":0,"scale":1,"position":{"pointX":319.912353515625,"pointY":22.5313720703125},"width":643,"sublayerTransform":[1,0,0,0,0,1,0,0,0,0,1,0,0,0,0,1],"contentsRect":{"y":0,"x":0,"width":1,"height":1},"opacity":1,"edgeAntialiasingMask":0,"height":49,"hidden":false,"anchorPoint":{"pointX":0.5,"pointY":0.5}},"texture":"EABA7B6053AB46FA718D41E94BE9775A"}]}]},{"animations":[],"initialState":{"affineTransform":[1,0,0,1,0,0],"masksToBounds":false,"rotation":0,"scale":1,"position":{"pointX":512,"pointY":384},"width":1024,"sublayerTransform":[1,0,0,0,0,1,0,0,0,0,1,0,0,0,0,1],"contentsRect":{"y":0,"x":0,"width":1,"height":1},"opacity":1,"edgeAntialiasingMask":15,"height":768,"hidden":false,"anchorPoint":{"pointX":0.5,"pointY":0.5}},"layers":[{"animations":[],"initialState":{"affineTransform":[1,0,0,1,0,0],"masksToBounds":false,"rotation":0,"scale":1,"position":{"pointX":145.3219459056854,"pointY":332.5658336281776},"width":90.09546041488647,"sublayerTransform":[1,0,0,0,0,1,0,0,0,0,1,0,0,0,0,1],"contentsRect":{"y":0,"x":0,"width":1,"height":1},"opacity":0.3331785500049591,"edgeAntialiasingMask":15,"height":45.08314430713654,"hidden":false,"anchorPoint":{"pointX":0.5,"pointY":0.5}},"objectID":"296FBA55-122C-429E-86FB-23582E5ED76E","layers":[{"animations":[],"layers":[],"initialState":{"affineTransform":[1,0,0,1,0,0],"masksToBounds":false,"rotation":0,"scale":1,"position":{"pointX":45.22578430175781,"pointY":22.97573852539062},"width":93,"sublayerTransform":[1,0,0,0,0,1,0,0,0,0,1,0,0,0,0,1],"contentsRect":{"y":0,"x":0,"width":1,"height":1},"opacity":1,"edgeAntialiasingMask":0,"height":48,"hidden":true,"anchorPoint":{"pointX":0.5,"pointY":0.5}},"texture":"2C9DB90032D83BB24BF98C4AE488D5EA"}]}]},{"animations":[],"initialState":{"affineTransform":[1,0,0,1,0,0],"masksToBounds":false,"rotation":0,"scale":1,"position":{"pointX":512,"pointY":384},"width":1024,"sublayerTransform":[1,0,0,0,0,1,0,0,0,0,1,0,0,0,0,1],"contentsRect":{"y":0,"x":0,"width":1,"height":1},"opacity":1,"edgeAntialiasingMask":15,"height":768,"hidden":false,"anchorPoint":{"pointX":0.5,"pointY":0.5}},"layers":[{"animations":[],"initialState":{"affineTransform":[1,0,0,1,0,0],"masksToBounds":false,"rotation":0,"scale":1,"position":{"pointX":190.897928237915,"pointY":580.1560741066933},"width":181.2474250793457,"sublayerTransform":[1,0,0,0,0,1,0,0,0,0,1,0,0,0,0,1],"contentsRect":{"y":0,"x":0,"width":1,"height":1},"opacity":0.3331785500049591,"edgeAntialiasingMask":15,"height":45.08314430713654,"hidden":false,"anchorPoint":{"pointX":0.5,"pointY":0.5}},"objectID":"480AFC97-2829-4EB4-A164-FF9D5C6DDD41","layers":[{"animations":[],"layers":[],"initialState":{"affineTransform":[1,0,0,1,0,0],"masksToBounds":false,"rotation":0,"scale":1,"position":{"pointX":90.72578430175781,"pointY":22.385498046875},"width":184,"sublayerTransform":[1,0,0,0,0,1,0,0,0,0,1,0,0,0,0,1],"contentsRect":{"y":0,"x":0,"width":1,"height":1},"opacity":1,"edgeAntialiasingMask":0,"height":48,"hidden":true,"anchorPoint":{"pointX":0.5,"pointY":0.5}},"texture":"D1A4DB96B5C9DBC588DC0D604E86AF00"}]}]},{"animations":[],"initialState":{"affineTransform":[1,0,0,1,0,0],"masksToBounds":false,"rotation":0,"scale":1,"position":{"pointX":512,"pointY":384},"width":1024,"sublayerTransform":[1,0,0,0,0,1,0,0,0,0,1,0,0,0,0,1],"contentsRect":{"y":0,"x":0,"width":1,"height":1},"opacity":1,"edgeAntialiasingMask":15,"height":768,"hidden":false,"anchorPoint":{"pointX":0.5,"pointY":0.5}},"layers":[{"animations":[],"initialState":{"affineTransform":[1,0,0,1,0,0],"masksToBounds":false,"rotation":0,"scale":1,"position":{"pointX":470.2907304763794,"pointY":97.06479352712631},"width":825.7207660675049,"sublayerTransform":[1,0,0,0,0,1,0,0,0,0,1,0,0,0,0,1],"contentsRect":{"y":0,"x":0,"width":1,"height":1},"opacity":1,"edgeAntialiasingMask":15,"height":95.86906611919403,"hidden":false,"anchorPoint":{"pointX":0.5,"pointY":0.5}},"objectID":"7FDEDC4A-7AC6-48C7-B69A-38F1F6ED0C7D","layers":[{"animations":[],"layers":[],"initialState":{"affineTransform":[1,0,0,1,0,0],"masksToBounds":false,"rotation":0,"scale":1,"position":{"pointX":94.56965255737305,"pointY":49.8697395324707},"width":174,"sublayerTransform":[1,0,0,0,0,1,0,0,0,0,1,0,0,0,0,1],"contentsRect":{"y":0,"x":0,"width":1,"height":1},"opacity":1,"edgeAntialiasingMask":0,"height":58,"hidden":false,"anchorPoint":{"pointX":0.5,"pointY":0.5}},"texture":"46B37BF333FDD983A8FBC88F1539B444"}]}]}]}},{"effects":[{"beginTime":0,"baseLayer":{"animations":[],"initialState":{"affineTransform":[1,0,0,1,0,0],"masksToBounds":true,"rotation":0,"scale":1,"position":{"pointX":512,"pointY":384},"width":1024,"sublayerTransform":[1,0,0,0,0,1,0,0,0,0,1,0,0,0,0,1],"contentsRect":{"y":0,"x":0,"width":1,"height":1},"opacity":1,"edgeAntialiasingMask":0,"height":768,"hidden":false,"anchorPoint":{"pointX":0.5,"pointY":0.5}},"objectID":"0","layers":[{"animations":[],"initialState":{"affineTransform":[1,0,0,1,0,0],"masksToBounds":false,"rotation":0,"scale":1,"position":{"pointX":512,"pointY":384},"width":1024,"sublayerTransform":[1,0,0,0,0,1,0,0,0,0,1,-0.0004922987690640373,0,0,0,1],"contentsRect":{"y":0,"x":0,"width":1,"height":1},"opacity":1,"edgeAntialiasingMask":15,"height":768,"hidden":false,"anchorPoint":{"pointX":0.5,"pointY":0.5}},"layers":[{"animations":[],"layers":[],"initialState":{"affineTransform":[1,0,0,1,0,0],"masksToBounds":false,"rotation":0,"scale":1,"position":{"pointX":512,"pointY":384},"width":1024,"sublayerTransform":[1,0,0,0,0,1,0,0,0,0,1,0,0,0,0,1],"contentsRect":{"y":0,"x":0,"width":1,"height":1},"opacity":1,"edgeAntialiasingMask":0,"height":768,"hidden":false,"anchorPoint":{"pointX":0.5,"pointY":0.5}},"texture":"B1BFF7B2FFA1C6EDC49D405D0E31B9AB"},{"animations":[{"from":{"scalar":false},"beginTime":0,"repeatCount":0,"fillMode":"both","property":"hidden","duration":0.01,"to":{"scalar":true}}],"layers":[],"initialState":{"affineTransform":[1,0,0,1,0,0],"masksToBounds":false,"rotation":0,"scale":1,"position":{"pointX":512,"pointY":384},"width":1024,"sublayerTransform":[1,0,0,0,0,1,0,0,0,0,1,0,0,0,0,1],"contentsRect":{"y":0,"x":0,"width":1,"height":1},"opacity":1,"edgeAntialiasingMask":0,"height":768,"hidden":false,"anchorPoint":{"pointX":0.5,"pointY":0.5}},"texture":"BDE3A89D37FB90520BA60BA16E672BEC"}]}]},"effects":[],"duration":0.01,"type":"transition","name":"none","objectID":"0"}],"automaticPlay":false,"hyperlinks":[],"accessibility":[{"text":"Node","targetRectangle":{"y":53.1302604675293,"x":61.43034744262695,"width":178.485,"height":88}},{"text":"var http   = require('http'),","targetRectangle":{"y":195.9999990463257,"x":69.56600952148438,"width":453.9462890625,"height":30}},{"text":"\t\t request = require('request');","targetRectangle":{"y":225.9999990463257,"x":69.56600952148438,"width":505.599609375,"height":30}},{"text":"http.createServer(function (req, res) {","targetRectangle":{"y":285.9999990463257,"x":69.56600952148438,"width":610.4794921875,"height":30}},{"text":"  try {","targetRectangle":{"y":315.9999990463257,"x":69.56600952148438,"width":109.5732421875,"height":30}},{"text":"    request.get('https://nodesource.com', function(e, r, b) { \u2028      throw new Error('Error');","targetRectangle":{"y":345.9999990463257,"x":69.56600952148438,"width":977.505859375,"height":70}},{"text":"      res.writeHead(200, {'Content-Type': 'text/plain'});","targetRectangle":{"y":415.9999990463257,"x":69.56600952148438,"width":892.2392578125,"height":30}},{"text":"      res.end('Length :' + b.length);","targetRectangle":{"y":445.9999990463257,"x":69.56600952148438,"width":579.1728515625,"height":30}},{"text":"                              ","targetRectangle":{"y":475.9999990463257,"x":69.56600952148438,"width":469.599609375,"height":30}},{"text":"    });","targetRectangle":{"y":505.9999990463257,"x":69.56600952148438,"width":109.5732421875,"height":30}},{"text":"  }\u2028  catch(e) {}","targetRectangle":{"y":535.9999990463257,"x":69.56600952148438,"width":203.4931640625,"height":60}},{"text":"}).listen(8000, '127.0.0.1');","targetRectangle":{"y":625.9999990463257,"x":69.56600952148438,"width":453.9462890625,"height":30}},{"text":"pasted-image.pdf","targetRectangle":{"y":702.7816162109375,"x":959.6049194335938,"width":56.26686477661133,"height":56.26686477661133}}],"baseLayer":{"animations":[],"initialState":{"affineTransform":[1,0,0,1,0,0],"masksToBounds":true,"rotation":0,"scale":1,"position":{"pointX":512,"pointY":384},"width":1024,"sublayerTransform":[1,0,0,0,0,1,0,0,0,0,1,0,0,0,0,1],"contentsRect":{"y":0,"x":0,"width":1,"height":1},"opacity":1,"edgeAntialiasingMask":0,"height":768,"hidden":false,"anchorPoint":{"pointX":0.5,"pointY":0.5}},"objectID":"0","layers":[{"animations":[],"initialState":{"affineTransform":[1,0,0,1,0,0],"masksToBounds":false,"rotation":0,"scale":1,"position":{"pointX":512,"pointY":384},"width":1024,"sublayerTransform":[1,0,0,0,0,1,0,0,0,0,1,-0.0004922987690640373,0,0,0,1],"contentsRect":{"y":0,"x":0,"width":1,"height":1},"opacity":1,"edgeAntialiasingMask":15,"height":768,"hidden":false,"anchorPoint":{"pointX":0.5,"pointY":0.5}},"layers":[{"animations":[],"layers":[],"initialState":{"affineTransform":[1,0,0,1,0,0],"masksToBounds":false,"rotation":0,"scale":1,"position":{"pointX":512,"pointY":384},"width":1024,"sublayerTransform":[1,0,0,0,0,1,0,0,0,0,1,0,0,0,0,1],"contentsRect":{"y":0,"x":0,"width":1,"height":1},"opacity":1,"edgeAntialiasingMask":0,"height":768,"hidden":false,"anchorPoint":{"pointX":0.5,"pointY":0.5}},"texture":"BDE3A89D37FB90520BA60BA16E672BEC"}]}]}}]}